fvm_nerfed/__init__.py
fvm_nerfed/run.py
fvm_nerfed-0.1.6.dist-info/entry_points.txt
fvm_nerfed-0.1.6.dist-info/WHEEL
fvm_nerfed-0.1.6.dist-info/METADATA
fvm_nerfed-0.1.6.dist-info/RECORD
